{
  "timestamp": "2026-03-03T09:07:22.095Z",
  "stocks": {
    "SPY": {
      "symbol": "SPY",
      "price": 686.3800048828125,
      "change": 0.056854276882997636,
      "timestamp": "2026-03-03T09:07:22.344Z"
    },
    "QQQ": {
      "symbol": "QQQ",
      "price": 608.0900268554688,
      "change": 0.13174082515305022,
      "timestamp": "2026-03-03T09:07:23.428Z"
    },
    "IWM": {
      "symbol": "IWM",
      "price": 263.80999755859375,
      "change": 0.9180956592566113,
      "timestamp": "2026-03-03T09:07:24.524Z"
    },
    "^VIX": {
      "symbol": "^VIX",
      "price": 25.309999465942383,
      "change": 18.050367702823703,
      "timestamp": "2026-03-03T09:07:25.582Z"
    }
  },
  "sentiment": {
    "score": 23,
    "label": "Bearish",
    "timestamp": "2026-03-03T09:07:26.583Z"
  },
  "fearGreed": {
    "value": 14,
    "classification": "Extreme Fear",
    "timestamp": "2026-03-03T09:07:26.850Z"
  },
  "putCallRatio": 1.1
}