{
  "timestamp": "2026-01-07T20:48:43.267Z",
  "stocks": {
    "SPY": {
      "symbol": "SPY",
      "price": 689.5599975585938,
      "change": -0.32523380811787606,
      "timestamp": "2026-01-07T20:48:43.438Z"
    },
    "QQQ": {
      "symbol": "QQQ",
      "price": 624.0599975585938,
      "change": 0.1026618757791303,
      "timestamp": "2026-01-07T20:48:44.508Z"
    },
    "IWM": {
      "symbol": "IWM",
      "price": 255.33999633789062,
      "change": -0.28896839783540645,
      "timestamp": "2026-01-07T20:48:45.615Z"
    },
    "^VIX": {
      "symbol": "^VIX",
      "price": 15.350000381469727,
      "change": 4.067799196404926,
      "timestamp": "2026-01-07T20:48:46.650Z"
    }
  },
  "sentiment": {
    "score": 43,
    "label": "Neutral",
    "timestamp": "2026-01-07T20:48:47.650Z"
  },
  "fearGreed": {
    "value": 42,
    "classification": "Fear",
    "timestamp": "2026-01-07T20:48:47.924Z"
  },
  "putCallRatio": 0.9
}