{
  "timestamp": "2026-02-15T08:58:44.590Z",
  "stocks": {
    "SPY": {
      "symbol": "SPY",
      "price": 681.75,
      "change": 0.07045377823616135,
      "timestamp": "2026-02-15T08:58:44.828Z"
    },
    "QQQ": {
      "symbol": "QQQ",
      "price": 601.9199829101562,
      "change": 0.2131007309707683,
      "timestamp": "2026-02-15T08:58:45.918Z"
    },
    "IWM": {
      "symbol": "IWM",
      "price": 262.9599914550781,
      "change": 1.3177093309543875,
      "timestamp": "2026-02-15T08:58:47.013Z"
    },
    "^VIX": {
      "symbol": "^VIX",
      "price": 20.600000381469727,
      "change": -1.056672990293959,
      "timestamp": "2026-02-15T08:58:48.074Z"
    }
  },
  "sentiment": {
    "score": 52,
    "label": "Neutral",
    "timestamp": "2026-02-15T08:58:49.075Z"
  },
  "fearGreed": {
    "value": 8,
    "classification": "Extreme Fear",
    "timestamp": "2026-02-15T08:58:49.346Z"
  },
  "putCallRatio": 0.9
}