{
  "timestamp": "2025-07-16T22:45:52.153Z",
  "data": {
    "symbol": "SPY",
    "current": {
      "date": "2025-07-16",
      "price": 624.22,
      "volume": 88025247,
      "change": 0.4800000000000182,
      "changePercent": 0.33
    },
    "historical": [
      {
        "date": "2025-07-16",
        "price": 624.22,
        "volume": 88025247,
        "change": 0.4800000000000182
      },
      {
        "date": "2025-07-15",
        "price": 622.14,
        "volume": 74317260,
        "change": -5.3799999999999955
      },
      {
        "date": "2025-07-14",
        "price": 624.81,
        "volume": 51898518,
        "change": 1.6499999999999773
      },
      {
        "date": "2025-07-11",
        "price": 623.62,
        "volume": 63670226,
        "change": 0.8799999999999955
      },
      {
        "date": "2025-07-10",
        "price": 625.82,
        "volume": 57528960,
        "change": 1.6200000000000045
      },
      {
        "date": "2025-07-09",
        "price": 624.06,
        "volume": 66113326,
        "change": 1.2899999999999636
      },
      {
        "date": "2025-07-08",
        "price": 620.34,
        "volume": 59024585,
        "change": -1.009999999999991
      },
      {
        "date": "2025-07-07",
        "price": 620.68,
        "volume": 74814505,
        "change": -2.6800000000000637
      },
      {
        "date": "2025-07-03",
        "price": 625.34,
        "volume": 51065789,
        "change": 2.8899999999999864
      },
      {
        "date": "2025-07-02",
        "price": 620.45,
        "volume": 66510374,
        "change": 3.2100000000000364
      },
      {
        "date": "2025-07-01",
        "price": 617.65,
        "volume": 70030140,
        "change": 1.2899999999999636
      },
      {
        "date": "2025-06-30",
        "price": 617.85,
        "volume": 92502541,
        "change": 0.4700000000000273
      },
      {
        "date": "2025-06-27",
        "price": 614.91,
        "volume": 86258398,
        "change": 2.0299999999999727
      },
      {
        "date": "2025-06-26",
        "price": 611.87,
        "volume": 78548361,
        "change": 2.8799999999999955
      },
      {
        "date": "2025-06-25",
        "price": 607.12,
        "volume": 62114767,
        "change": -0.7899999999999636
      },
      {
        "date": "2025-06-24",
        "price": 606.78,
        "volume": 67735293,
        "change": 2.449999999999932
      },
      {
        "date": "2025-06-23",
        "price": 600.15,
        "volume": 87426039,
        "change": 5.110000000000014
      },
      {
        "date": "2025-06-20",
        "price": 594.28,
        "volume": 94051374,
        "change": -4.100000000000023
      },
      {
        "date": "2025-06-18",
        "price": 597.44,
        "volume": 76605029,
        "change": -1
      },
      {
        "date": "2025-06-17",
        "price": 597.53,
        "volume": 82209365,
        "change": -2.6800000000000637
      },
      {
        "date": "2025-06-16",
        "price": 602.68,
        "volume": 79984125,
        "change": 2.2799999999999727
      },
      {
        "date": "2025-06-13",
        "price": 597,
        "volume": 89505996,
        "change": -1.5
      },
      {
        "date": "2025-06-12",
        "price": 603.75,
        "volume": 64129003,
        "change": 3.740000000000009
      },
      {
        "date": "2025-06-11",
        "price": 601.36,
        "volume": 73658225,
        "change": -2.830000000000041
      },
      {
        "date": "2025-06-10",
        "price": 603.08,
        "volume": 66246973,
        "change": 2.8600000000000136
      },
      {
        "date": "2025-06-09",
        "price": 599.68,
        "volume": 53016418,
        "change": -0.04000000000007731
      },
      {
        "date": "2025-06-06",
        "price": 599.14,
        "volume": 66588743,
        "change": 0.4800000000000182
      },
      {
        "date": "2025-06-05",
        "price": 593.05,
        "volume": 92436397,
        "change": -4.580000000000041
      },
      {
        "date": "2025-06-04",
        "price": 595.93,
        "volume": 57314199,
        "change": -1.0300000000000864
      },
      {
        "date": "2025-06-03",
        "price": 596.09,
        "volume": 63606204,
        "change": 3.75
      }
    ],
    "lastUpdated": "2025-07-16T22:45:52.153Z"
  }
}