{
  "timestamp": "2026-06-29T12:46:07.067Z",
  "stocks": {
    "SPY": {
      "symbol": "SPY",
      "price": 728.989990234375,
      "change": -0.7231373616869609,
      "timestamp": "2026-06-29T12:46:07.455Z"
    },
    "QQQ": {
      "symbol": "QQQ",
      "price": 706.52001953125,
      "change": -1.3763624451209278,
      "timestamp": "2026-06-29T12:46:08.662Z"
    },
    "IWM": {
      "symbol": "IWM",
      "price": 299.8299865722656,
      "change": 0.30777923083370845,
      "timestamp": "2026-06-29T12:46:09.809Z"
    },
    "^VIX": {
      "symbol": "^VIX",
      "price": 18.280000686645508,
      "change": -0.7061334157744468,
      "timestamp": "2026-06-29T12:46:10.851Z"
    }
  },
  "sentiment": {
    "score": 48,
    "label": "Neutral",
    "timestamp": "2026-06-29T12:46:11.852Z"
  },
  "fearGreed": {
    "value": 12,
    "classification": "Extreme Fear",
    "timestamp": "2026-06-29T12:46:12.050Z"
  },
  "putCallRatio": 1.05
}